Workbook

Sheet Vendas
A1: ID_Venda | B1: Data | C1: Produto | D1: Categoria | E1: Quantidade | F1: Preco_Unitario | G1: Desconto | H1: Cidade | I1: Estado | J1: Forma_Pagamento | K1: Vendedor | L1: Faturamento
A2: 1 | B2: 45658 | C2: Notebook | D2: Informática | E2: 9 | F2: 3500 | G2: 0.14 | H2: Caruaru | I2: PE | J2: Boleto | K2: Bruno | L2: =E2*F2*(1-G2) -> 27090
A3: 2 | B3: 45659 | C3: Smartphone | D3: Celulares | E3: 6 | F3: 1800 | G3: 0.05 | H3: Salvador | I3: BA | J3: Boleto | K3: Carla | L3: =E3*F3*(1-G3) -> 10260
A4: 3 | B4: 45660 | C4: Smartphone | D4: Celulares | E4: 1 | F4: 1800 | G4: 0.08 | H4: Fortaleza | I4: CE | J4: Cartão de débito | K4: Bruno | L4: =E4*F4*(1-G4) -> 1656
A5: 4 | B5: 45661 | C5: Notebook | D5: Informática | E5: 8 | F5: 3500 | G5: 0.04 | H5: Juazeiro do Norte | I5: CE | J5: Boleto | K5: Carla | L5: =E5*F5*(1-G5) -> 26880
A6: 5 | B6: 45662 | C6: Smartphone | D6: Celulares | E6: 7 | F6: 1800 | G6: 0.04 | H6: Feira de Santana | I6: BA | J6: Boleto | K6: Carla | L6: =E6*F6*(1-G6) -> 12096
A7: 6 | B7: 45663 | C7: Headset | D7: Periféricos | E7: 4 | F7: 250 | G7: 0.02 | H7: Campina Grande | I7: PB | J7: Pix | K7: Fernanda | L7: =E7*F7*(1-G7) -> 980
A8: 7 | B8: 45664 | C8: Notebook | D8: Informática | E8: 10 | F8: 3500 | G8: 0.14 | H8: Recife | I8: PE | J8: Boleto | K8: Fernanda | L8: =E8*F8*(1-G8) -> 30100
A9: 8 | B9: 45665 | C9: Smartphone | D9: Celulares | E9: 4 | F9: 1800 | G9: 0.06 | H9: Fortaleza | I9: CE | J9: Pix | K9: Carla | L9: =E9*F9*(1-G9) -> 6768
A10: 9 | B10: 45666 | C10: Notebook | D10: Informática | E10: 4 | F10: 3500 | G10: 0.01 | H10: Salvador | I10: BA | J10: Cartão de débito | K10: Diego | L10: =E10*F10*(1-G10) -> 13860
A11: 10 | B11: 45667 | C11: Notebook | D11: Informática | E11: 3 | F11: 3500 | G11: 0.12 | H11: Recife | I11: PE | J11: Cartão de débito | K11: Ana | L11: =E11*F11*(1-G11) -> 9240
A12: 11 | B12: 45668 | C12: Smartphone | D12: Celulares | E12: 8 | F12: 1800 | G12: 0.13 | H12: Salvador | I12: BA | J12: Pix | K12: Fernanda | L12: =E12*F12*(1-G12) -> 12528
A13: 12 | B13: 45669 | C13: Smartphone | D13: Celulares | E13: 6 | F13: 1800 | G13: 0.06 | H13: Juazeiro do Norte | I13: CE | J13: Pix | K13: Ana | L13: =E13*F13*(1-G13) -> 10152
... A101: 100 | B101: 45757 | C101: Headset | D101: Periféricos | E101: 4 | F101: 250 | G101: 0.13 | H101: Natal | I101: RN | J101: Pix | K101: Bruno | L101: =E101*F101*(1-G101) -> 870

Sheet Listas
A1: Produtos | B1: Categorias | C1: Estados | D1: Formas_Pagamento | E1: Vendedores | F1: Preco_Unitario | G1: Estado | H1: Cidade
A2: Notebook | B2: Informática | C2: PE | D2: Pix | E2: Ana | F2: 3500 | G2: PE | H2: Recife
A3: Smartphone | B3: Celulares | C3: BA | D3: Cartão de crédito | E3: Bruno | F3: 1800 | G3: PE | H3: Caruaru
A4: Monitor | B4: Monitores | C4: CE | D4: Cartão de débito | E4: Carla | F4: 1200 | G4: BA | H4: Salvador
A5: Teclado | B5: Periféricos | C5: AL | D5: Boleto | E5: Diego | F5: 150 | G5: BA | H5: Feira de Santana
A6: Mouse | C6: PB | E6: Fernanda | F6: 80 | G6: CE | H6: Fortaleza
A7: Headset | C7: RN | F7: 250 | G7: CE | H7: Juazeiro do Norte
G8: AL | H8: Maceió
G9: AL | H9: Arapiraca
G10: PB | H10: João Pessoa
G11: PB | H11: Campina Grande
G12: RN | H12: Natal
G13: RN | H13: Mossoró

Sheet Indicadores
A1: Indicador | B1: Valor | D1: Produto | E1: Faturamento | G1: Vendedor | H1: Faturamento | J1: Vendedor | K1: Quantidade de Vendas | M1: Estado | N1: Faturamento | P1: Mês | Q1: Faturamento
A2: Faturamento Total | B2: =SUM(Vendas!L2:L101) -> 627895.4 | D2: Notebook | E2: =SUMIF(Vendas!$C$2:$C$101,D2,Vendas!$L$2:$L$101) -> 370650 | G2: Ana | H2: =SUMIF(Vendas!$K$2:$K$101,G2,Vendas!$L$2:$L$101) -> 78304.8 | J2: Ana | K2: =COUNTIF(Vendas!$K$2:$K$101,J2) -> 15 | M2: PE | N2: =SUMIF(Vendas!$I$2:$I$101,M2,Vendas!$L$2:$L$101) -> 99332.8 | P2: Janeiro | Q2: =SUMIFS(Vendas!$L$2:$L$101,Vendas!$B$2:$B$101,">="&DATE(2025,1,1),Vendas!$B$2:$B$101,"<"&DATE(2025,2,1)) -> 247510.8
A3: Quantidade de Vendas | B3: =COUNTA(Vendas!A2:A101) -> 100 | D3: Smartphone | E3: =SUMIF(Vendas!$C$2:$C$101,D3,Vendas!$L$2:$L$101) -> 173880 | G3: Bruno | H3: =SUMIF(Vendas!$K$2:$K$101,G3,Vendas!$L$2:$L$101) -> 118652.6 | J3: Bruno | K3: =COUNTIF(Vendas!$K$2:$K$101,J3) -> 21 | M3: BA | N3: =SUMIF(Vendas!$I$2:$I$101,M3,Vendas!$L$2:$L$101) -> 121590.8 | P3: Fevereiro | Q3: =SUMIFS(Vendas!$L$2:$L$101,Vendas!$B$2:$B$101,">="&DATE(2025,2,1),Vendas!$B$2:$B$101,"<"&DATE(2025,3,1)) -> 150729.1
A4: Unidades Vendidas | B4: =SUM(Vendas!E2:E101) -> 510 | D4: Monitor | E4: =SUMIF(Vendas!$C$2:$C$101,D4,Vendas!$L$2:$L$101) -> 43668 | G4: Carla | H4: =SUMIF(Vendas!$K$2:$K$101,G4,Vendas!$L$2:$L$101) -> 143971.9 | J4: Carla | K4: =COUNTIF(Vendas!$K$2:$K$101,J4) -> 30 | M4: CE | N4: =SUMIF(Vendas!$I$2:$I$101,M4,Vendas!$L$2:$L$101) -> 97626.1 | P4: Março | Q4: =SUMIFS(Vendas!$L$2:$L$101,Vendas!$B$2:$B$101,">="&DATE(2025,3,1),Vendas!$B$2:$B$101,"<"&DATE(2025,4,1)) -> 182158.7
A5: Ticket Médio | B5: =B2/B3 -> 6278.954 | D5: Teclado | E5: =SUMIF(Vendas!$C$2:$C$101,D5,Vendas!$L$2:$L$101) -> 14029.5 | G5: Diego | H5: =SUMIF(Vendas!$K$2:$K$101,G5,Vendas!$L$2:$L$101) -> 127121.8 | J5: Diego | K5: =COUNTIF(Vendas!$K$2:$K$101,J5) -> 17 | M5: AL | N5: =SUMIF(Vendas!$I$2:$I$101,M5,Vendas!$L$2:$L$101) -> 104907.8 | P5: Abril | Q5: =SUMIFS(Vendas!$L$2:$L$101,Vendas!$B$2:$B$101,">="&DATE(2025,4,1),Vendas!$B$2:$B$101,"<"&DATE(2025,5,1)) -> 47496.8
D6: Mouse | E6: =SUMIF(Vendas!$C$2:$C$101,D6,Vendas!$L$2:$L$101) -> 4590.4 | G6: Fernanda | H6: =SUMIF(Vendas!$K$2:$K$101,G6,Vendas!$L$2:$L$101) -> 159844.3 | J6: Fernanda | K6: =COUNTIF(Vendas!$K$2:$K$101,J6) -> 17 | M6: PB | N6: =SUMIF(Vendas!$I$2:$I$101,M6,Vendas!$L$2:$L$101) -> 96768
D7: Headset | E7: =SUMIF(Vendas!$C$2:$C$101,D7,Vendas!$L$2:$L$101) -> 21077.5 | M7: RN | N7: =SUMIF(Vendas!$I$2:$I$101,M7,Vendas!$L$2:$L$101) -> 107669.9
